mnfinder/__init__.py
mnfinder/classifiers.py
mnfinder/kerasmodels.py
mnfinder/mnfinder.py
mnfinder/segmenters.py
mnfinder/test-data/image-info.csv
mnfinder/test-data/2022-10-14_U2OS/4.psp
mnfinder/test-data/2022-10-14_U2OS/images/4.png
mnfinder/test-data/2022-10-14_U2OS/images/4.tif
mnfinder/test-data/2022-10-14_U2OS/mn_masks/4.png
mnfinder/test-data/2022-10-14_U2OS/nucleus_masks/4.png
mnfinder/test-data/2023-05-31_misc/1.psp
mnfinder/test-data/2023-05-31_misc/HFF-revt-01_s17.psp
mnfinder/test-data/2023-05-31_misc/HFF-revt-01_s18.psp
mnfinder/test-data/2023-05-31_misc/HFF-revt-01_s19.psp
mnfinder/test-data/2023-05-31_misc/HFF-revt-01_s5.psp
mnfinder/test-data/2023-05-31_misc/MAX_2021_1_12_BAY18_CREST647_chr18_568_h3kac488_DAPI_20x-20x_DAPI.psp
mnfinder/test-data/2023-05-31_misc/MAX_2021_1_12_BAY18_CREST647_chr18_568_h3kac488_DAPI_20x-Series003-1.psp
mnfinder/test-data/2023-05-31_misc/MAX_2021_3_11_heladcas9_1_chr1CLING568_h2b488_40x.psp
mnfinder/test-data/2023-05-31_misc/MAX_2021_3_25_hela_misseg_dcas9_1_chr1XCE568_DAPI_40x-0002.psp
mnfinder/test-data/2023-05-31_misc/MAX_2021_3_25_hela_misseg_dcas9_1_chr1XCE568_DAPI_40xlif - Series001.psp
mnfinder/test-data/2023-05-31_misc/MAX_2022-12-29 ATF3 tilescanlif - BAY.psp
mnfinder/test-data/2023-05-31_misc/MAX_2022-12-29-0004.psp
mnfinder/test-data/2023-05-31_misc/MCC13_rfpcyto_w1cDAPI_s43.psp
mnfinder/test-data/2023-05-31_misc/MCC13_rfpcyto_w1cDAPI_s45.psp
mnfinder/test-data/2023-05-31_misc/MCC13_rfpcyto_w1cDAPI_s47.psp
mnfinder/test-data/2023-05-31_misc/images/1.png
mnfinder/test-data/2023-05-31_misc/images/1.tif
mnfinder/test-data/2023-05-31_misc/images/HFF-revt-01_s17.png
mnfinder/test-data/2023-05-31_misc/images/HFF-revt-01_s17.tif
mnfinder/test-data/2023-05-31_misc/images/HFF-revt-01_s18.png
mnfinder/test-data/2023-05-31_misc/images/HFF-revt-01_s18.tif
mnfinder/test-data/2023-05-31_misc/images/HFF-revt-01_s19.png
mnfinder/test-data/2023-05-31_misc/images/HFF-revt-01_s19.tif
mnfinder-1.2.3.dist-info/METADATA
mnfinder-1.2.3.dist-info/WHEEL
mnfinder-1.2.3.dist-info/licenses/LICENSE.py
mnfinder-1.2.3.dist-info/RECORD
