Metadata-Version: 2.3
Name: mnfinder
Version: 1.2.3
Summary: A package for segmenting micronuclei in microscopy images
Project-URL: Homepage, https://github.com/hatch-lab/mnfinder
Author-email: Lucian DiPeso <ldipeso@uw.edu>
License-File: LICENSE.py
Keywords: U-Net,micronuclei,micronucleus,segmentation
Classifier: License :: OSI Approved :: MIT License
Classifier: Operating System :: OS Independent
Classifier: Programming Language :: Python :: 3
Requires-Python: >3.11
Requires-Dist: albumentations
Requires-Dist: cdboundary
Requires-Dist: csbdeep
Requires-Dist: docopt
Requires-Dist: jupyter
Requires-Dist: numpy
Requires-Dist: opencv-contrib-python
Requires-Dist: pandas
Requires-Dist: pillow
Requires-Dist: platformdirs
Requires-Dist: pydot
Requires-Dist: scikit-image
Requires-Dist: tensorflow==2.16.1
Requires-Dist: tifffile
Requires-Dist: tqdm
